{
  "arxiv_id": "2603.01009",
  "title": "Qayyem: A Real-time Platform for Scoring Proficiency of Arabic Essays",
  "abstract": "Over the past years, Automated Essay Scoring (AES) systems have gained increasing attention as scalable and consistent solutions for assessing the proficiency of student writing. Despite recent progress, support for Arabic AES remains limited due to linguistic complexity and scarcity of large publicly-available annotated datasets. In this work, we present Qayyem, a Web-based platform designed to support Arabic AES by providing an integrated workflow for assignment creation, batch essay upload, scoring configuration, and per-trait essay evaluation. Qayyem abstracts the technical complexity of interacting with scoring server APIs, allowing instructors to access advanced scoring services through a user-friendly interface. The platform deploys a number of state-of-the-art Arabic essay scoring models with different effectiveness and efficiency figures.",
  "authors": [
    null
  ],
  "categories": "cs.CL",
  "created": "2026-05-19",
  "fetched_at": "2026-05-21T23:03:18.615605"
}